orionbot.py
orionbot-1.2.1.dist-info/WHEEL
orionbot-1.2.1.dist-info/METADATA
orionbot-1.2.1.dist-info/RECORD
