Metadata-Version: 2.1
Name: orionbot
Version: 1.2.1
Summary: orionbot - a simple chatbot training framework
Author-email: Lyubomir Ternavskiy <ternavski103@gmail.com>
Classifier: Development Status :: 4 - Beta
Classifier: Programming Language :: Python
Requires-Dist: nltk
Requires-Dist: scikit-learn
